RayZuijiaShijianZhinanFix1/README.md
RayZuijiaShijianZhinanFix1/__init__.py
RayZuijiaShijianZhinanFix1/__main__.py
RayZuijiaShijianZhinanFix1/file.epub
RayZuijiaShijianZhinanFix1/index.html
RayZuijiaShijianZhinanFix1/css/__init__.py
RayZuijiaShijianZhinanFix1/css/annotations.css
RayZuijiaShijianZhinanFix1/css/main.css
RayZuijiaShijianZhinanFix1/css/normalize.css
RayZuijiaShijianZhinanFix1/css/popup.css
RayZuijiaShijianZhinanFix1/font/__init__.py
RayZuijiaShijianZhinanFix1/font/fontello.eot
RayZuijiaShijianZhinanFix1/font/fontello.svg
RayZuijiaShijianZhinanFix1/font/fontello.ttf
RayZuijiaShijianZhinanFix1/font/fontello.woff
RayZuijiaShijianZhinanFix1/img/__init__.py
RayZuijiaShijianZhinanFix1/img/annotator-glyph-sprite.png
RayZuijiaShijianZhinanFix1/img/annotator-icon-sprite.png
RayZuijiaShijianZhinanFix1/img/apple-touch-icon.png
RayZuijiaShijianZhinanFix1/img/cancelfullscreen.png
RayZuijiaShijianZhinanFix1/img/close.png
RayZuijiaShijianZhinanFix1/img/fullscreen.png
RayZuijiaShijianZhinanFix1/img/loader.gif
RayZuijiaShijianZhinanFix1/img/menu-icon.png
RayZuijiaShijianZhinanFix1/img/save.png
RayZuijiaShijianZhinanFix1/img/saved.png
RayZuijiaShijianZhinanFix1/img/settings-s.png
RayZuijiaShijianZhinanFix1/img/settings.png
RayZuijiaShijianZhinanFix1/img/star.png
RayZuijiaShijianZhinanFix1/js/__init__.py
RayZuijiaShijianZhinanFix1/js/epub.js
RayZuijiaShijianZhinanFix1/js/epub.min.js
RayZuijiaShijianZhinanFix1/js/epub.min.map
RayZuijiaShijianZhinanFix1/js/hooks.min.js
RayZuijiaShijianZhinanFix1/js/hooks.min.map
RayZuijiaShijianZhinanFix1/js/reader.js
RayZuijiaShijianZhinanFix1/js/reader.js.map
RayZuijiaShijianZhinanFix1/js/reader.min.js
RayZuijiaShijianZhinanFix1/js/reader.min.map
RayZuijiaShijianZhinanFix1/js/hooks/__init__.py
RayZuijiaShijianZhinanFix1/js/hooks/extensions/__init__.py
RayZuijiaShijianZhinanFix1/js/hooks/extensions/highlight.js
RayZuijiaShijianZhinanFix1/js/libs/__init__.py
RayZuijiaShijianZhinanFix1/js/libs/jquery.min.js
ray_zuijia_shijian_zhinan_fix1-2025.3.25.0.dist-info/METADATA
ray_zuijia_shijian_zhinan_fix1-2025.3.25.0.dist-info/WHEEL
ray_zuijia_shijian_zhinan_fix1-2025.3.25.0.dist-info/entry_points.txt
ray_zuijia_shijian_zhinan_fix1-2025.3.25.0.dist-info/top_level.txt
ray_zuijia_shijian_zhinan_fix1-2025.3.25.0.dist-info/RECORD
